dailyquotes-0.1.1.dist-info/licenses/LICENSE
quotes/__init__.py
quotes/chatgpt.py
quotes/fallback.py
quotes/generator.py
dailyquotes-0.1.1.dist-info/METADATA
dailyquotes-0.1.1.dist-info/WHEEL
dailyquotes-0.1.1.dist-info/top_level.txt
dailyquotes-0.1.1.dist-info/RECORD
