Metadata-Version: 2.4
Name: DailyQuotes
Version: 0.1.1
Summary: DailyQuotes is a simple Python package that generates random quotes including quotes that are well-known, from celebrities, mood-based, and in different languages. This Python package provides an easy way to integrate meaningful quotes into projects, daily routines, or personal motivation.
Home-page: https://github.com/yourusername/quotes-generator
Author: Your Name
Author-email: Andy Cabindol <acc7936@nyu.edu>, Maya Mabry <mam10023@nyu.edu>, Aaqila Patel <amp10098@nyu.edu>, Lina Sanchez <lhs9817@nyu.edu>
License: MIT
Requires-Python: >=3.7
License-File: LICENSE
Requires-Dist: setuptools
Requires-Dist: python-dotenv
Requires-Dist: openai
Provides-Extra: dev
Requires-Dist: pytest; extra == "dev"
Dynamic: author
Dynamic: home-page
Dynamic: license-file
Dynamic: requires-python
